omigo_hydra/__init__.py
omigo_hydra/cluster_arjun.py
omigo_hydra/cluster_class_reflection.py
omigo_hydra/cluster_common_v2.py
omigo_hydra/cluster_data.py
omigo_hydra/cluster_funcs.py
omigo_hydra/cluster_protocol_v2.py
omigo_hydra/cluster_services_v2.py
omigo_hydra/cluster_shell_ext.py
omigo_hydra/cluster_tsv.py
omigo_hydra/etl.py
omigo_hydra/file_io_wrapper.py
omigo_hydra/file_paths_data_reader.py
omigo_hydra/file_paths_reader.py
omigo_hydra/file_paths_util.py
omigo_hydra/hydra.py
omigo_hydra/local_fs_wrapper.py
omigo_hydra/non_cluster_job_runner.py
omigo_hydra/s3_wrapper.py
omigo_hydra/s3io_wrapper.py
omigo_hydra-0.9.2.dist-info/METADATA
omigo_hydra-0.9.2.dist-info/WHEEL
omigo_hydra-0.9.2.dist-info/top_level.txt
omigo_hydra-0.9.2.dist-info/RECORD
